ellalgo/__init__.py
ellalgo/conjugate_gradient.py
ellalgo/cutting_plane.py
ellalgo/ell.py
ellalgo/ell1d.tpy
ellalgo/ell_calc.py
ellalgo/ell_calc.tpy
ellalgo/ell_calc_core.py
ellalgo/ell_config.py
ellalgo/ell_stable.py
ellalgo/ell_typing.py
ellalgo/skeleton.py
ellalgo/oracles/ldlt_mgr.py
ellalgo/oracles/lmi0_oracle.py
ellalgo/oracles/lmi2_oracle.tpy
ellalgo/oracles/lmi3_oracle.tpy
ellalgo/oracles/lmi_old_oracle.py
ellalgo/oracles/lmi_oracle.py
ellalgo/oracles/lowpass_oracle.py
ellalgo/oracles/profit_oracle.py
ellalgo-0.3.dist-info/licenses/LICENSE.txt
ellalgo-0.3.dist-info/METADATA
ellalgo-0.3.dist-info/WHEEL
ellalgo-0.3.dist-info/top_level.txt
ellalgo-0.3.dist-info/RECORD
